cwam/__init__.py
cwam/alarm.py
cwam/alb.py
cwam/cli.py
cwam/client.py
cwam/cloudwatch.py
cwam/cwam.py
cwam/default_alarm.py
cwam/ec2.py
cwam/ecs.py
cwam/elasticache.py
cwam/elb.py
cwam/kinesis.py
cwam/pgbouncer.py
cwam/rds.py
cwam/utils.py
cwam-2.0.dist-info/METADATA
cwam-2.0.dist-info/RECORD
cwam-2.0.dist-info/WHEEL
cwam-2.0.dist-info/entry_points.txt
cwam-2.0.dist-info/top_level.txt
