Metadata-Version: 2.1
Name: cwam
Version: 2.0
Summary: Easy way to create default CloudWatch Alarms.
Home-page: https://github.com/instacart/cwam
Author: Quentin Rousseau
Author-email: quentin@instacart.com
License: MIT license
Keywords: cloudwatch
Platform: UNKNOWN
Classifier: Development Status :: 5 - Production/Stable
Classifier: Intended Audience :: Developers
Classifier: License :: OSI Approved :: MIT License
Classifier: Natural Language :: English
Classifier: Programming Language :: Python :: 2.6
Classifier: Programming Language :: Python :: 2.7
Classifier: Programming Language :: Python :: 2
Classifier: Programming Language :: Python :: 3.3
Classifier: Programming Language :: Python :: 3.4
Classifier: Programming Language :: Python :: 3.5
Classifier: Programming Language :: Python :: 3.6
Classifier: Programming Language :: Python :: 3
Classifier: Topic :: Internet :: WWW/HTTP
Classifier: Topic :: Software Development
Classifier: Topic :: System :: Monitoring
Requires-Dist: Click (>=7.0)
Requires-Dist: boto3 (>=1.4.3)
Requires-Dist: dictdiffer (>=0.6.1)
Requires-Dist: PyYAML (>=3.12)
